tarkus/tarkus.base.yml
tarkus/tarkus.py
tarkus/__init__.py
tarkus/__main__.py
Tarkus-0.9.1.data/scripts/tarkus.bat
Tarkus-0.9.1.dist-info/DESCRIPTION.rst
Tarkus-0.9.1.dist-info/METADATA
Tarkus-0.9.1.dist-info/metadata.json
Tarkus-0.9.1.dist-info/RECORD
Tarkus-0.9.1.dist-info/top_level.txt
Tarkus-0.9.1.dist-info/WHEEL
