Metadata-Version: 2.0
Name: Tarkus
Version: 0.9.1
Summary: IDA Pro Plugin Manager
Home-page: https://github.com/tmr232/Tarkus
Author: Tamir Bahar
Author-email: UNKNOWN
License: MIT
Platform: UNKNOWN
Requires-Dist: docopt
Requires-Dist: pip
Requires-Dist: GitPython
Requires-Dist: PyYAML
Requires-Dist: attrdict
Requires-Dist: awesomelib
